when_keyword/__init__.py
when_keyword-0.1.0.dist-info/licenses/LICENSE
when_keyword-0.1.0.dist-info/METADATA
when_keyword-0.1.0.dist-info/WHEEL
when_keyword-0.1.0.dist-info/top_level.txt
when_keyword-0.1.0.dist-info/RECORD
